sphinxcontrib_jupyter-0.5.10-py3.7-nspkg.pth
sphinxcontrib/jupyter/__init__.py
sphinxcontrib/jupyter/builders/__init__.py
sphinxcontrib/jupyter/builders/jupyter.py
sphinxcontrib/jupyter/builders/jupyterpdf.py
sphinxcontrib/jupyter/directive/__init__.py
sphinxcontrib/jupyter/directive/exercise.py
sphinxcontrib/jupyter/directive/jupyter.py
sphinxcontrib/jupyter/transform/__init__.py
sphinxcontrib/jupyter/writers/__init__.py
sphinxcontrib/jupyter/writers/convert.py
sphinxcontrib/jupyter/writers/execute_nb.py
sphinxcontrib/jupyter/writers/jupyter.py
sphinxcontrib/jupyter/writers/make_pdf.py
sphinxcontrib/jupyter/writers/make_site.py
sphinxcontrib/jupyter/writers/translate_all.py
sphinxcontrib/jupyter/writers/translate_code.py
sphinxcontrib/jupyter/writers/utils.py
sphinxcontrib_jupyter-0.5.10.dist-info/LICENSE
sphinxcontrib_jupyter-0.5.10.dist-info/METADATA
sphinxcontrib_jupyter-0.5.10.dist-info/WHEEL
sphinxcontrib_jupyter-0.5.10.dist-info/namespace_packages.txt
sphinxcontrib_jupyter-0.5.10.dist-info/top_level.txt
sphinxcontrib_jupyter-0.5.10.dist-info/RECORD
